slippistats/__init__.py
slippistats/actions.py
slippistats/combos.py
slippistats/common.py
slippistats/conversions.py
slippistats/factory.py
slippistats/inputs.py
slippistats/overall.py
slippistats/slippitypes.py
slippistats/stats.py
slippistats/stocks.py
py_slippi_stats-0.0.2.dist-info/LICENSE
py_slippi_stats-0.0.2.dist-info/METADATA
py_slippi_stats-0.0.2.dist-info/WHEEL
py_slippi_stats-0.0.2.dist-info/top_level.txt
py_slippi_stats-0.0.2.dist-info/RECORD
