Metadata-Version: 2.1
Name: py-slippi-stats
Version: 0.0.2
Summary: A package for getting Slippi stats in Python
Home-page: https://gitlab.com/oneshineman/py-slippi-stats
Author: Diego Arana Segura
Author-email: diego.arana.segura@gmail.com
License: UNKNOWN
Project-URL: Bug Tracker, https://gitlab.com/oneshineman/py-slippi-stats/issues
Platform: UNKNOWN
Classifier: Programming Language :: Python :: 3
Classifier: License :: OSI Approved :: MIT License
Classifier: Operating System :: OS Independent
Requires-Python: >=3.6
Requires-Dist: py-slippi (==1.6.1)
Requires-Dist: py-ubjson (==0.16.1)
Requires-Dist: termcolor (==1.1.0)
